setup.py
digReadabilityExtractor/__init__.py
digReadabilityExtractor/readability_extractor.py
digReadabilityExtractor.egg-info/PKG-INFO
digReadabilityExtractor.egg-info/SOURCES.txt
digReadabilityExtractor.egg-info/dependency_links.txt
digReadabilityExtractor.egg-info/requires.txt
digReadabilityExtractor.egg-info/top_level.txt
digReadabilityExtractor/readability/__init__.py
digReadabilityExtractor/readability/cleaners.py
digReadabilityExtractor/readability/debug.py
digReadabilityExtractor/readability/encoding.py
digReadabilityExtractor/readability/htmls.py
digReadabilityExtractor/readability/readability.py
test/test_readability_extractor.py