Metadata-Version: 1.1
Name: digReadabilityExtractor
Version: 0.3.0
Summary: digReadabilityExtractor
Home-page: https://github.com/usc-isi-i2/dig-readability-extractor
Author: Jason Slepicka
Author-email: jasonslepicka@gmail.com
License: UNKNOWN
Download-URL: https://github.com/usc-isi-i2/dig-readability-extractor
Platform: UNKNOWN
